barnhunt-1.2.1rc3.dist-info/METADATA
barnhunt-1.2.1rc3.dist-info/WHEEL
barnhunt-1.2.1rc3.dist-info/entry_points.txt
barnhunt-1.2.1rc3.dist-info/licenses/LICENSE
barnhunt/__init__.py
barnhunt/__main__.py
barnhunt/_compat.py
barnhunt/_version.py
barnhunt/cli.py
barnhunt/coursemaps.py
barnhunt/inkscape/__init__.py
barnhunt/inkscape/css.py
barnhunt/inkscape/runner.py
barnhunt/inkscape/svg.py
barnhunt/inkscape/utils.py
barnhunt/installer/__init__.py
barnhunt/installer/github.py
barnhunt/installer/metadata.py
barnhunt/layerinfo.py
barnhunt/pager.py
barnhunt/pdfutil.py
barnhunt/templating.py
barnhunt-1.2.1rc3.dist-info/RECORD
