Metadata-Version: 2.1
Name: barnhunt
Version: 1.2.1rc3
Summary: Helpers for drawing Barn Hunt course maps using Inkscape
Keywords: barn hunt inkscape course maps
Author-Email: Jeff Dairiki <dairiki@dairiki.org>
License: GPL-3.0-only
Classifier: Development Status :: 4 - Beta
Classifier: Environment :: Console
Classifier: Intended Audience :: End Users/Desktop
Classifier: License :: OSI Approved :: BSD License
Classifier: Programming Language :: Python :: 3
Classifier: Topic :: Multimedia :: Graphics :: Graphics Conversion
Classifier: Topic :: Printing
Classifier: Topic :: Utilities
Project-URL: Homepage, https://github.com/barnhunt/barnhunt
Requires-Python: >=3.7
Requires-Dist: atomicwrites~=1.4
Requires-Dist: click~=8.1
Requires-Dist: importlib-metadata==4; python_version < "3.10"
Requires-Dist: jinja2~=3.1
Requires-Dist: lxml~=4.9
Requires-Dist: marshmallow~=3.19
Requires-Dist: marshmallow-dataclass~=8.5.13
Requires-Dist: packaging~=23.1
Requires-Dist: pexpect~=4.8
Requires-Dist: pikepdf~=6.2
Requires-Dist: rdflib~=6.3
Requires-Dist: requests~=2.29
Requires-Dist: tinycss2~=1.2
Requires-Dist: typing-extensions~=4.5; python_version < "3.10"
